jsonclasses_pymongo/__init__.py
jsonclasses_pymongo/base_object.py
jsonclasses_pymongo/coder.py
jsonclasses_pymongo/command.py
jsonclasses_pymongo/connection.py
jsonclasses_pymongo/context.py
jsonclasses_pymongo/dbconf.py
jsonclasses_pymongo/decoder.py
jsonclasses_pymongo/encoder.py
jsonclasses_pymongo/exceptions.py
jsonclasses_pymongo/excs.py
jsonclasses_pymongo/pconf.py
jsonclasses_pymongo/pobject.py
jsonclasses_pymongo/preload.py
jsonclasses_pymongo/py.typed
jsonclasses_pymongo/pymongo.py
jsonclasses_pymongo/pymongo_object.py
jsonclasses_pymongo/pymongofy.py
jsonclasses_pymongo/query.py
jsonclasses_pymongo/query_reader.py
jsonclasses_pymongo/query_to_object.py
jsonclasses_pymongo/readers.py
jsonclasses_pymongo/unused_include.py
jsonclasses_pymongo/utils.py
tests/__init__.py
tests/test_complete.py
tests/test_decoder.py
tests/test_delete.py
tests/test_encoder.py
tests/test_include.py
tests/test_object_include.py
tests/test_preload.py
tests/test_query.py
tests/test_query_include.py
tests/test_save.py
tests/test_strid.py
tests/test_unique_records.py
tests/classes/__init__.py
tests/classes/chained_user.py
tests/classes/linked_account.py
tests/classes/linked_album.py
tests/classes/linked_author.py
tests/classes/linked_bomb.py
tests/classes/linked_favorite.py
tests/classes/linked_hiphop_song.py
tests/classes/linked_music_product.py
tests/classes/linked_notebook.py
tests/classes/linked_order.py
tests/classes/linked_pop_singer.py
tests/classes/linked_post.py
tests/classes/linked_profile_user.py
tests/classes/linked_record.py
tests/classes/linked_share.py
tests/classes/linked_song.py
tests/classes/linked_strid.py
tests/classes/linked_todo_list.py
tests/classes/links_preload.py
tests/classes/preload.py
tests/classes/simple_album.py
tests/classes/simple_animal.py
tests/classes/simple_artist.py
tests/classes/simple_calcuser.py
tests/classes/simple_date.py
tests/classes/simple_datetime.py
tests/classes/simple_hiphop_album.py
tests/classes/simple_person.py
jsonclasses_pymongo-3.3.0.dist-info/LICENSE
jsonclasses_pymongo-3.3.0.dist-info/METADATA
jsonclasses_pymongo-3.3.0.dist-info/WHEEL
jsonclasses_pymongo-3.3.0.dist-info/top_level.txt
jsonclasses_pymongo-3.3.0.dist-info/RECORD
