Metadata-Version: 2.1
Name: jsonclasses-pymongo
Version: 3.3.0
Summary: jsonclasses integration with pymongo
Home-page: https://github.com/fillmula/jsonclasses-pymongo
Author: Fillmula Inc.
Author-email: victor.teo@fillmula.com
License: MIT
Platform: UNKNOWN
Requires-Python: >=3.10
License-File: LICENSE
Requires-Dist: pymongo (<5.0.0,>=4.0.1)
Requires-Dist: inflection-plus (<2.0.0,>=0.1.0)
Requires-Dist: qsparser (<2.0.0,>=1.1.0)
